jmpr/__init__.py
jmpr/cli.py
jmpr/cloudassets.py
jmpr/jmprGui.py
jmpr/policies.py
jmpr-0.3.1.dist-info/LICENSE
jmpr-0.3.1.dist-info/METADATA
jmpr-0.3.1.dist-info/WHEEL
jmpr-0.3.1.dist-info/entry_points.txt
jmpr-0.3.1.dist-info/top_level.txt
jmpr-0.3.1.dist-info/RECORD
