Metadata-Version: 2.1
Name: jmpr
Version: 0.3.1
Summary: Tooling to permit AWS account navigation
Home-page: https://github.com/eGT-Labs/jmpr
Author: eGT Labs
Author-email: egtlabs@eglobaltech.com
License: GPL-3.0-only
Platform: UNKNOWN
Classifier: Programming Language :: Python :: 3
Classifier: Development Status :: 4 - Beta
Classifier: Environment :: Console
Classifier: Natural Language :: English
Classifier: License :: OSI Approved :: GNU General Public License v3 or later (GPLv3+)
Classifier: Operating System :: OS Independent
Classifier: Topic :: Utilities
Requires-Dist: boto3
Requires-Dist: pyyaml
